AUTHORS
LICENSE
README.txt
ez_setup.py
setup.cfg
setup.py
examples/support-threaded.py
examples/support-twisted.py
examples/support-uthreaded.py
test/__init__.py
test/test_uthreads.py
uthreads/__init__.py
uthreads/core.py
uthreads/sync.py
uthreads/timer.py
uthreads.egg-info/PKG-INFO
uthreads.egg-info/SOURCES.txt
uthreads.egg-info/dependency_links.txt
uthreads.egg-info/requires.txt
uthreads.egg-info/top_level.txt
uthreads.egg-info/zip-safe
wiki/MotivatingExample.wiki
wiki/StandardMicrothreadingPattern.wiki
wiki/UthreadsApi.wiki