Metadata-Version: 1.0
Name: uthreads
Version: 1.0
Summary: Python Microthreading Library
Home-page: http://code.google.com/p/uthreads
Author: Dustin J. Mitchell
Author-email: dustin@cs.uchicago.edu
License: UNKNOWN
Platform: UNKNOWN
Classifier: Framework :: Twisted
Classifier: Intended Audience :: Developers
Classifier: License :: OSI Approved :: GNU General Public License (GPL)
Classifier: Programming Language :: Python
Classifier: Topic :: Software Development :: Libraries :: Python Modules
